cellucid/__init__.py
cellucid/anndata_variations.py
cellucid/prepare_data.py
cellucid/repo_to_text.py
cellucid-0.0.1a0.dist-info/METADATA
cellucid-0.0.1a0.dist-info/WHEEL
cellucid-0.0.1a0.dist-info/top_level.txt
cellucid-0.0.1a0.dist-info/RECORD
