Metadata-Version: 2.4
Name: cellucid
Version: 0.0.1a0
Summary: Utilities to export data for the 3D UMAP WebGL viewer.
Author: cellucid contributors
License: Proprietary
Project-URL: Repository, https://github.com/theislab/cellucid-data
Classifier: Programming Language :: Python :: 3
Classifier: Programming Language :: Python :: 3 :: Only
Classifier: License :: Other/Proprietary License
Classifier: Intended Audience :: Science/Research
Classifier: Topic :: Scientific/Engineering :: Visualization
Classifier: Topic :: Scientific/Engineering :: Bio-Informatics
Requires-Python: >=3.10
Requires-Dist: numpy>=1.22
Requires-Dist: pandas>=1.5
Requires-Dist: scipy>=1.9
Requires-Dist: tqdm>=4.66
Provides-Extra: analysis
Requires-Dist: anndata>=0.10; extra == "analysis"
Requires-Dist: scanpy>=1.10; extra == "analysis"
Provides-Extra: docs
Requires-Dist: sphinx>=7.2; extra == "docs"
Requires-Dist: myst-parser>=2.0; extra == "docs"
Requires-Dist: sphinx-autodoc-typehints>=1.25; extra == "docs"
Requires-Dist: sphinx_rtd_theme>=1.3; extra == "docs"
